nest/__init__.py
nest/goa.py
nest/methods.py
nest/benchmarks/__init__.py
nest/benchmarks/agglomerative.py
nest/benchmarks/comparison.py
nest/benchmarks/parameters_synthetic.py
nest/benchmarks/parameters_synthetic_segmentation.py
nest/benchmarks/subsampling.py
nest/benchmarks/synthetic_analysis.py
nest/cci/__init__.py
nest/cci/cci.py
nest/cci/cellchat.py
nest/cci/spatial.py
nest/data/__init__.py
nest/data/data.py
nest/data/database.py
nest/hmrf/__init__.py
nest/hmrf/hmrf.py
nest/hotspot/__init__.py
nest/hotspot/coexpression.py
nest/hotspot/geometry.py
nest/hotspot/hotspot.py
nest/hotspot/hotspots_3d.py
nest/hotspot/interaction_hotspot.py
nest/plot/__init__.py
nest/plot/hotspots.py
nest/plot/pl3d.py
nest/plot/plot.py
nest/plot/tracksplot.py
nest/utility/__init__.py
nest/utility/utility.py
nest_analysis-1.0.4.dist-info/LICENSE
nest_analysis-1.0.4.dist-info/METADATA
nest_analysis-1.0.4.dist-info/WHEEL
nest_analysis-1.0.4.dist-info/top_level.txt
nest_analysis-1.0.4.dist-info/RECORD
