Metadata-Version: 2.1
Name: nest-analysis
Version: 1.0.4
Summary: NeST method for identifying nested structure in spatial transcriptomic data
License-File: LICENSE
